claudewarp/__init__.py
claudewarp/util.py
claudewarp/cli/__init__.py
claudewarp/cli/commands.py
claudewarp/cli/formatters.py
claudewarp/cli/main.py
claudewarp/core/__init__.py
claudewarp/core/config.py
claudewarp/core/exceptions.py
claudewarp/core/manager.py
claudewarp/core/models.py
claudewarp/core/utils.py
claudewarp-0.1.4.dist-info/METADATA
claudewarp-0.1.4.dist-info/WHEEL
claudewarp-0.1.4.dist-info/entry_points.txt
claudewarp-0.1.4.dist-info/licenses/LICENSE
claudewarp-0.1.4.dist-info/RECORD
