Metadata-Version: 2.4
Name: claudewarp
Version: 0.1.4
Summary: Claude API proxy management tool with CLI and GUI
Project-URL: Homepage, https://github.com/belingud/claudewarp
Project-URL: Repository, https://github.com/belingud/claudewarp
Project-URL: Issues, https://github.com/belingud/claudewarp/issues
Project-URL: Documentation, https://github.com/belingud/claudewarp
Author-email: claudewarp <im.victor@qq.com>
License-Expression: MIT
License-File: LICENSE
Keywords: api,claude,cli,gui,management,proxy
Classifier: Development Status :: 3 - Alpha
Classifier: Intended Audience :: Developers
Classifier: License :: OSI Approved :: MIT License
Classifier: Operating System :: OS Independent
Classifier: Programming Language :: Python :: 3
Classifier: Programming Language :: Python :: 3.8
Classifier: Programming Language :: Python :: 3.9
Classifier: Programming Language :: Python :: 3.10
Classifier: Programming Language :: Python :: 3.11
Classifier: Programming Language :: Python :: 3.12
Classifier: Topic :: Software Development :: Libraries :: Python Modules
Classifier: Topic :: Utilities
Requires-Python: >=3.8
Requires-Dist: colorlog>=6.0.0
Requires-Dist: pydantic-core>=2.27.2
Requires-Dist: pydantic<3.0.0,>=2.0.0
Requires-Dist: rich>=13.0.0
Requires-Dist: toml>=0.10.0
Requires-Dist: typer>=0.16.0
